ralipyard-0.1.0.dist-info/METADATA
ralipyard-0.1.0.dist-info/WHEEL
ralipyard-0.1.0.dist-info/license_files/LICENSE
ralipyard/__init__.py
ralipyard/__init__.pyi
ralipyard/py.typed
ralipyard/ralipyard.pypy37-pp73-x86_64-linux-gnu.so
ralipyard-0.1.0.dist-info/RECORD
