Metadata-Version: 2.1
Name: ralipyard
Version: 0.1.0
Classifier: Programming Language :: Rust
Classifier: Programming Language :: Python :: Implementation :: CPython
Classifier: Programming Language :: Python :: Implementation :: PyPy
Classifier: Framework :: AsyncIO
Requires-Dist: pytest==7.1.2; extra == 'test'
Requires-Dist: pytest-asyncio==0.18.3; extra == 'test'
Provides-Extra: test
License-File: LICENSE
Summary: Thread-safe rate limit semaphore for threading and async/await style built on  Rust
Keywords: async,semaphore,threading,rate,limit
Author-email: dekno@gmail.com
Requires-Python: >=3.7
Project-URL: homepage, https://github.com/deknowny/ralipyard
Project-URL: repository, https://github.com/deknowny/ralipyard
Project-URL: documentation, https://github.com/deknowny/ralipyard/blob/main/ralipyard.pyi
